ginny/__init__.py
ginny/argo.py
ginny/base.py
ginny/docker.py
ginny/loader.py
ginny/log.py
ginny/s3.py
ginny/schedule.py
ginny/ssh.py
ginny/utils.py
ginny/version.py
ginny/vis.py
ginny-0.1.1.dist-info/METADATA
ginny-0.1.1.dist-info/WHEEL
ginny-0.1.1.dist-info/entry_points.txt
ginny-0.1.1.dist-info/top_level.txt
ginny-0.1.1.dist-info/RECORD
