Metadata-Version: 2.2
Name: ginny
Version: 0.1.1
Summary: run and schedule task pipeline
Home-page: https://github.com/baudcode/ginny
Author: Malte Koch
Author-email: malte-koch@gmx.net
Maintainer: Malte Koch
Maintainer-email: malte-koch@gmx.net
License: MIT
Keywords: task,worker,schedule,machine,learning
Classifier: Development Status :: 3 - Alpha
Classifier: Intended Audience :: Developers
Classifier: Operating System :: POSIX :: Linux
Classifier: License :: OSI Approved :: GNU General Public License v3 (GPLv3)
Classifier: Programming Language :: Python :: 3
Requires-Dist: boto3
Requires-Dist: tqdm
Requires-Dist: ujson
Requires-Dist: pillow
Requires-Dist: numpy
Requires-Dist: networkx
Requires-Dist: schedule
Requires-Dist: pydantic
Requires-Dist: requests
Requires-Dist: pyyaml
Provides-Extra: extra
Requires-Dist: paramiko; extra == "extra"
Requires-Dist: docker; extra == "extra"
Dynamic: author
Dynamic: author-email
Dynamic: classifier
Dynamic: description
Dynamic: description-content-type
Dynamic: home-page
Dynamic: keywords
Dynamic: license
Dynamic: maintainer
Dynamic: maintainer-email
Dynamic: provides-extra
Dynamic: requires-dist
Dynamic: summary
